drf_authentify/__init__.py
drf_authentify/admin.py
drf_authentify/apps.py
drf_authentify/auth.py
drf_authentify/choices.py
drf_authentify/compat.py
drf_authentify/contexts.py
drf_authentify/forms.py
drf_authentify/managers.py
drf_authentify/models.py
drf_authentify/services.py
drf_authentify/settings.py
drf_authentify/types.py
drf_authentify/utils.py
drf_authentify/validators.py
drf_authentify/migrations/0001_initial.py
drf_authentify/migrations/__init__.py
drf_authentify-0.5.7.dist-info/licenses/LICENSE
drf_authentify-0.5.7.dist-info/METADATA
drf_authentify-0.5.7.dist-info/WHEEL
drf_authentify-0.5.7.dist-info/top_level.txt
drf_authentify-0.5.7.dist-info/RECORD
