Metadata-Version: 2.4
Name: drf-authentify
Version: 0.5.7
Summary: A simple authentication module for django rest framework
Author: Gabriel Idenyi
License: BSD 3-Clause License
Project-URL: Homepage, https://github.com/idenyigabriel/drf-authentify
Project-URL: Documentation, https://github.com/idenyigabriel/drf-authentify/blob/main/README.md
Project-URL: Repository, https://github.com/idenyigabriel/drf-authentify
Project-URL: Issues, https://github.com/idenyigabriel/drf-authentify/issues
Project-URL: Changelog, https://github.com/idenyigabriel/drf-authentify/blob/main/CHANGELOG.md
Keywords: django,djangorestframework,drf,authentication
Classifier: Development Status :: 4 - Beta
Classifier: Environment :: Web Environment
Classifier: Framework :: Django
Classifier: Framework :: Django :: 4.2
Classifier: Framework :: Django :: 5.2
Classifier: Intended Audience :: Developers
Classifier: License :: OSI Approved :: BSD License
Classifier: Natural Language :: English
Classifier: Operating System :: OS Independent
Classifier: Programming Language :: Python
Classifier: Programming Language :: Python :: 3
Classifier: Programming Language :: Python :: 3 :: Only
Classifier: Programming Language :: Python :: 3.8
Classifier: Programming Language :: Python :: 3.9
Classifier: Programming Language :: Python :: 3.10
Classifier: Programming Language :: Python :: 3.11
Classifier: Programming Language :: Python :: 3.12
Classifier: Programming Language :: Python :: 3.13
Classifier: Topic :: Internet :: WWW/HTTP
Classifier: Topic :: Internet :: WWW/HTTP :: Session
Requires-Python: >=3.9
License-File: LICENSE
Requires-Dist: Django>=4.2
Requires-Dist: djangorestframework>=3.1
Requires-Dist: typing_extensions; python_version < "3.11"
Dynamic: license-file
